{
  "identity": {
    "fund_id": "INF966L01580",
    "name": "Quant Multi Asset Allocation Fund Direct Growth",
    "category": "Hybrid",
    "amc_name": "Quant Mutual Fund",
    "benchmark_name": "Groww Debt Benchmark",
    "plan_label": "Growth",
    "keywords": [
      "Quant Multi Asset",
      "Quant Allocation",
      "Quant Hybrid",
      "Multi asset fund",
      "Quant Mutual Fund"
    ]
  },
  "nav": {
    "value": 175.3572,
    "date": "30-Apr-2026",
    "high_52w": null,
    "high_52w_date": null,
    "low_52w": null,
    "low_52w_date": null
  },
  "returns": {
    "one_year": 22.34,
    "three_year": 23.98,
    "five_year": 23.31,
    "since_inception": 9.86,
    "benchmark_one_year": null,
    "benchmark_three_year": null,
    "benchmark_five_year": null,
    "category_avg_one_year": 15.094648397077961,
    "category_avg_three_year": 17.808079513027074,
    "category_avg_five_year": 16.11038377499498
  },
  "risk": {
    "riskometer": "High",
    "standard_deviation": 12.037949588339776,
    "sharpe_ratio": 1.3708009222,
    "beta": 0,
    "alpha": 0
  },
  "portfolio": {
    "top_holdings": [
      {
        "name": "Nippon India ETF Gold BeES",
        "percentage": null,
        "weight_pct": 9.770773,
        "sector": null
      },
      {
        "name": "HDFC Bank Ltd.",
        "percentage": null,
        "weight_pct": 8.539186,
        "sector": null
      },
      {
        "name": "ICICI Bank Ltd.",
        "percentage": null,
        "weight_pct": 7.118641,
        "sector": null
      },
      {
        "name": "Kotak Mahindra Bank Ltd.",
        "percentage": null,
        "weight_pct": 6.38185,
        "sector": null
      },
      {
        "name": "HDFC Life Insurance Co Ltd.",
        "percentage": null,
        "weight_pct": 5.613865,
        "sector": null
      },
      {
        "name": "Aurobindo Pharma Ltd.",
        "percentage": null,
        "weight_pct": 4.973908,
        "sector": null
      },
      {
        "name": "Premier Energies Ltd.",
        "percentage": null,
        "weight_pct": 4.482039,
        "sector": null
      },
      {
        "name": "Bajaj Finance Ltd.",
        "percentage": null,
        "weight_pct": 3.767882,
        "sector": null
      },
      {
        "name": "ICICI Prudential Asset Management Company Ltd.",
        "percentage": null,
        "weight_pct": 3.704458,
        "sector": null
      },
      {
        "name": "Adani Green Energy Ltd.",
        "percentage": null,
        "weight_pct": 2.6423,
        "sector": null
      }
    ],
    "asset_allocation": {
      "equity": null,
      "debt": null,
      "cash": null,
      "others": null
    },
    "total_stocks": null,
    "total_bonds": null,
    "sector_allocation": {},
    "turnover_ratio": 0
  },
  "operations": {
    "expense_ratio": 0.6,
    "exit_load": "Exit load of 1%, if redeemed within 15 days.",
    "min_investment": {
      "sip": 1000,
      "lumpsum": 5000
    },
    "fund_size_cr": null,
    "launch_date": null,
    "taxation": "If you redeem within two years, returns are taxed as per your Income Tax slab. If you redeem after two years, returns are taxed at 12.5%."
  },
  "fund_manager": {
    "name": "Varun Pattani",
    "tenure": null,
    "tenure_years": null,
    "experience_summary": "Prior to joining Quant Mutual Fund, he has worked with boutique PMS firm.",
    "other_funds_managed": [
      "Quant Aggressive Hybrid Fund Direct Growth",
      "Quant Multi Asset Allocation Fund Direct Growth",
      "Quant Multi Cap Fund Direct Growth",
      "Quant Large and Mid Cap Fund Direct Growth",
      "Quant Small Cap Fund Direct Plan Growth",
      "Quant Infrastructure Fund Direct Growth",
      "Quant Focused Fund Direct Growth",
      "Quant Mid Cap Fund Direct Growth",
      "Quant Flexi Cap Fund Direct Growth",
      "Quant ELSS Tax Saver Fund Direct Growth",
      "Quant ESG Integration Strategy Fund Direct Growth",
      "Quant Quantamental Fund Direct Growth",
      "Quant Value Fund Direct Growth",
      "Quant Large Cap Fund Direct Growth",
      "Quant Dynamic Asset Allocation Fund Direct Growth",
      "Quant Business Cycle Fund Direct Growth",
      "Quant BFSI Fund Direct Growth",
      "Quant Healthcare Fund Direct Growth",
      "Quant Manufacturing Fund Direct Growth",
      "Quant Teck Fund Direct Growth",
      "Quant Momentum Fund Direct Growth",
      "Quant Commodities Fund Direct Growth",
      "Quant Consumption Fund Direct Growth",
      "Quant PSU Fund Direct Growth",
      "Quant Equity Savings Fund Direct Growth"
    ]
  },
  "news_context": [
    {
      "headline": "Latest mutual fund & market news",
      "date": null,
      "publisher": "Groww News",
      "summary": "Generic news stream from Groww; not specific to this single fund.",
      "url": "https://groww.in/blog/category/news"
    }
  ],
  "source_urls": [
    "https://groww.in/mutual-funds/quant-multi-asset-allocation-fund-direct-growth"
  ],
  "last_scraped_at": "2026-05-04T04:58:10.511466Z"
}